{
  "key": "Incarnate.Destiny",
  "display_name": "Destiny",
  "help": "Incarnate",
  "short_help": "Incarnate",
  "icon": "destiny_set.ico",
  "powers": [
    "Ageless_Core_Epiphany",
    "Ageless_Core_Invocation",
    "Ageless_Invocation",
    "Ageless_Partial_Core_Invocation",
    "Ageless_Partial_Radial_Invocation",
    "Ageless_Radial_Epiphany",
    "Ageless_Radial_Invocation",
    "Ageless_Total_Core_Invocation",
    "Ageless_Total_Radial_Invocation",
    "Barrier_Core_Epiphany",
    "Barrier_Core_Invocation",
    "Barrier_Invocation",
    "Barrier_Partial_Core_Invocation",
    "Barrier_Partial_Radial_Invocation",
    "Barrier_Radial_Epiphany",
    "Barrier_Radial_Invocation",
    "Barrier_Total_Core_Invocation",
    "Barrier_Total_Radial_Invocation",
    "Clarion_Core_Epiphany",
    "Clarion_Core_Invocation",
    "Clarion_Invocation",
    "Clarion_Partial_Core_Invocation",
    "Clarion_Partial_Radial_Invocation",
    "Clarion_Radial_Epiphany",
    "Clarion_Radial_Invocation",
    "Clarion_Total_Core_Invocation",
    "Clarion_Total_Radial_Invocation",
    "Incandescence_Core_Epiphany",
    "Incandescence_Core_Invocation",
    "Incandescence_Invocation",
    "Incandescence_Partial_Core_Invocation",
    "Incandescence_Partial_Radial_Invocation",
    "Incandescence_Radial_Epiphany",
    "Incandescence_Radial_Invocation",
    "Incandescence_Total_Core_Invocation",
    "Incandescence_Total_Radial_Invocation",
    "Rebirth_Core_Epiphany",
    "Rebirth_Core_Invocation",
    "Rebirth_Invocation",
    "Rebirth_Partial_Core_Invocation",
    "Rebirth_Partial_Radial_Invocation",
    "Rebirth_Radial_Epiphany",
    "Rebirth_Radial_Invocation",
    "Rebirth_Total_Core_Invocation",
    "Rebirth_Total_Radial_Invocation"
  ],
  "available_level": [
    0,
    0,
    0,
    0,
    0,
    0,
    0,
    0,
    0,
    0,
    0,
    0,
    0,
    0,
    0,
    0,
    0,
    0,
    0,
    0,
    0,
    0,
    0,
    0,
    0,
    0,
    0,
    0,
    0,
    0,
    0,
    0,
    0,
    0,
    0,
    0,
    0,
    0,
    0,
    0,
    0,
    0,
    0,
    0,
    0
  ]
}