{
  "key": "Controller_Buff.Darkness_Affinity",
  "display_name": "Darkness Affinity",
  "help": "Focus the dark power of the Netherworld to weaken your foes and aid your allies. Darkness Affinity focuses on draining your opponent.",
  "short_help": "Darkness Affinity",
  "icon": "darkness_affinity_set.ico",
  "powers": [
    "Controller_Buff.Darkness_Affinity.Black_Hole",
    "Controller_Buff.Darkness_Affinity.Dark_Servant",
    "Controller_Buff.Darkness_Affinity.Darkest_Night",
    "Controller_Buff.Darkness_Affinity.Fade",
    "Controller_Buff.Darkness_Affinity.Howling_Twilight",
    "Controller_Buff.Darkness_Affinity.Shadow_Fall",
    "Controller_Buff.Darkness_Affinity.Soul_Absorption",
    "Controller_Buff.Darkness_Affinity.Tar_Patch",
    "Controller_Buff.Darkness_Affinity.Twilight_Grasp"
  ],
  "available_level": [
    27,
    29,
    3,
    19,
    9,
    15,
    23,
    0,
    0
  ],
  "power_display_names": [
    "Black Hole",
    "Dark Servant",
    "Darkest Night",
    "Fade",
    "Howling Twilight",
    "Shadow Fall",
    "Soul Absorption",
    "Tar Patch",
    "Twilight Grasp"
  ],
  "power_short_helps": [
    "Ranged (Targeted AoE), Foe Intangible",
    "Summon Dark Servant: Ranged Debuff Special",
    "Toggle: Ranged (Targeted AoE), Foe -DMG, -To Hit",
    "PBAoE Ally, +Defense(All), +Res(Defense Debuffs, Lethal, Smash, Negative, Psionic)",
    "Ranged (AoE), Minor DMG(Negative), Target Slow, -Recharge, -Regen, Disorient, Ally Rez",
    "Toggle: PBAoE, Team Stealth, +DEF(All), +Res(Energy, Negative, Psionics, Fear)",
    "PBAoE Team +Regen, +Recovery, Foe -To Hit",
    "Ranged (Location AoE), Target -Speed, -Res, -Fly",
    "Ranged, Foe -To Hit, -DMG, -Regen, Team Heal"
  ]
}