{
  "key": "Brute_Melee.Martial_Arts",
  "display_name": "Martial Arts",
  "help": "A compilation of various fighting techniques from around the world, Martial Arts makes you a master in the art of hand to hand combat. Martial Artists tend to be very accurate with their strikes.",
  "short_help": "Martial Arts",
  "icon": "martial_arts_set.ico",
  "powers": [
    "Brute_Melee.Martial_Arts.Cobra_Strike",
    "Brute_Melee.Martial_Arts.Crane_Kick",
    "Brute_Melee.Martial_Arts.Crippling_Axe_Kick",
    "Brute_Melee.Martial_Arts.Dragons_Tail",
    "Brute_Melee.Martial_Arts.Eagles_Claw",
    "Brute_Melee.Martial_Arts.Focus_Chi",
    "Brute_Melee.Martial_Arts.Storm_Kick",
    "Brute_Melee.Martial_Arts.Thunder_Kick",
    "Brute_Melee.Martial_Arts.Warriors_Provocation"
  ],
  "available_level": [
    1,
    7,
    17,
    21,
    25,
    5,
    0,
    0,
    11
  ]
}