{
  "name": "Increase_Density",
  "full_name": "Controller_Buff.Kinetics.Increase_Density",
  "short_name": "Increase_Density",
  "type": "Click",
  "display_name": "Increase Density",
  "display_fullname": "Controller Buff Kinetics Increase Density",
  "display_help": "C7NFBLH3YLEHYJBRCYU84KG7Z2",
  "display_short_help": "Ranged, Ally Special",
  "icon": "kineticboost_increasedensity.png",
  "auto_issue": false,
  "auto_issue_keeps_level": false,
  "accuracy": 1.0,
  "effect_area": "Sphere",
  "max_targets_hit": 255,
  "radius": 30.0,
  "arc": 0.0,
  "range": 70.0,
  "range_secondary": 0.0,
  "activation_time": 2.07,
  "recharge_time": 3.0,
  "activate_period": 0.0,
  "endurance_cost": 5.2,
  "interrupt_time": 0.0,
  "target_type": "Friend",
  "target_type_secondary": "None",
  "targets_autohit": [
    "Friend"
  ],
  "targets_affected": [
    "Friend"
  ],
  "boosts_allowed": [
    "Res_Damage",
    "EnduranceDiscount",
    "Range",
    "Recharge"
  ],
  "allowed_boostset_cats": [],
  "cast_through": [],
  "num_allowed": 1,
  "requires": "",
  "activate_requires": "",
  "target_requires": "",
  "attack_types": [],
  "effects": [
    {
      "chance": 1.0,
      "ppm": 0.0,
      "delay": 0.0,
      "radius_inner": -1.0,
      "radius_outer": -1.0,
      "requires_expression": "",
      "flags": [],
      "is_pvp": "EITHER",
      "eval_flags": 0,
      "templates": [
        {
          "attribs": [
            "Smashing_Dmg",
            "Energy_Dmg"
          ],
          "type": "Magnitude",
          "application_type": "Immediate",
          "aspect": "Resistance",
          "target": "AnyAffected",
          "table": "Ranged_Res_Dmg",
          "scale": 2.5,
          "duration": "60 seconds",
          "magnitude": 1.0,
          "delay": 0.0,
          "duration_expression": "",
          "magnitude_expression": "",
          "application_period": 0.0,
          "tick_chance": 1.0,
          "tick_mag_multiplier": 1.0,
          "tick_mag_additive": 0.0,
          "jit_requires": "",
          "caster_stack": "Individual",
          "stack": "Replace",
          "stack_limit": 2,
          "stack_key": null
        }
      ]
    },
    {
      "chance": 1.0,
      "ppm": 0.0,
      "delay": 0.0,
      "radius_inner": -1.0,
      "radius_outer": -1.0,
      "requires_expression": "",
      "flags": [],
      "is_pvp": "EITHER",
      "eval_flags": 0,
      "templates": [
        {
          "attribs": [
            "Held",
            "Immobilized",
            "Stunned"
          ],
          "type": "Magnitude",
          "application_type": "Immediate",
          "aspect": "Current",
          "target": "AnyAffected",
          "table": "Ranged_Res_Boolean",
          "scale": -30.0,
          "duration": "60 seconds",
          "magnitude": 1.0,
          "delay": 0.0,
          "duration_expression": "",
          "magnitude_expression": "",
          "application_period": 0.0,
          "tick_chance": 1.0,
          "tick_mag_multiplier": 1.0,
          "tick_mag_additive": 0.0,
          "jit_requires": "",
          "caster_stack": "Individual",
          "stack": "Stack",
          "stack_limit": 2,
          "stack_key": null
        }
      ]
    },
    {
      "chance": 1.0,
      "ppm": 0.0,
      "delay": 0.0,
      "radius_inner": -1.0,
      "radius_outer": -1.0,
      "requires_expression": "",
      "flags": [],
      "is_pvp": "EITHER",
      "eval_flags": 0,
      "templates": [
        {
          "attribs": [
            "Held",
            "Immobilized",
            "Stunned"
          ],
          "type": "Magnitude",
          "application_type": "Immediate",
          "aspect": "Resistance",
          "target": "AnyAffected",
          "table": "Ranged_Res_Boolean",
          "scale": 3.0,
          "duration": "60 seconds",
          "magnitude": 1.0,
          "delay": 0.0,
          "duration_expression": "",
          "magnitude_expression": "",
          "application_period": 0.0,
          "tick_chance": 1.0,
          "tick_mag_multiplier": 1.0,
          "tick_mag_additive": 0.0,
          "jit_requires": "",
          "caster_stack": "Individual",
          "stack": "Stack",
          "stack_limit": 2,
          "stack_key": null
        },
        {
          "attribs": [
            "Held",
            "Immobilized",
            "Stunned"
          ],
          "type": "Magnitude",
          "application_type": "Immediate",
          "aspect": "Current",
          "target": "AnyAffected",
          "table": "Ranged_Res_Boolean",
          "scale": -25.0,
          "duration": "60 seconds",
          "magnitude": 1.0,
          "delay": 0.0,
          "duration_expression": "",
          "magnitude_expression": "",
          "application_period": 0.0,
          "tick_chance": 1.0,
          "tick_mag_multiplier": 1.0,
          "tick_mag_additive": 0.0,
          "jit_requires": "",
          "caster_stack": "Unlimited",
          "stack": "Suppress",
          "stack_limit": 2,
          "stack_key": "thColumn.5thColumnEndgame.NictusFX"
        }
      ]
    },
    {
      "chance": 1.0,
      "ppm": 0.0,
      "delay": 0.0,
      "radius_inner": -1.0,
      "radius_outer": -1.0,
      "requires_expression": "",
      "flags": [],
      "is_pvp": "EITHER",
      "eval_flags": 0,
      "templates": [
        {
          "attribs": [
            "Knockup",
            "Knockback",
            "Repel"
          ],
          "type": "Magnitude",
          "application_type": "Immediate",
          "aspect": "Current",
          "target": "AnyAffected",
          "table": "Ranged_Ones",
          "scale": -8.0,
          "duration": "60 seconds",
          "magnitude": 1.0,
          "delay": 0.0,
          "duration_expression": "",
          "magnitude_expression": "",
          "application_period": 0.0,
          "tick_chance": 1.0,
          "tick_mag_multiplier": 1.0,
          "tick_mag_additive": 0.0,
          "jit_requires": "",
          "caster_stack": "Individual",
          "stack": "Stack",
          "stack_limit": 2,
          "stack_key": null
        },
        {
          "attribs": [
            "Teleport"
          ],
          "type": "Magnitude",
          "application_type": "Immediate",
          "aspect": "Resistance",
          "target": "AnyAffected",
          "table": "Ranged_Ones",
          "scale": 1.0,
          "duration": "60 seconds",
          "magnitude": 1.0,
          "delay": 0.0,
          "duration_expression": "",
          "magnitude_expression": "",
          "application_period": 0.0,
          "tick_chance": 1.0,
          "tick_mag_multiplier": 1.0,
          "tick_mag_additive": 0.0,
          "jit_requires": "",
          "caster_stack": "Individual",
          "stack": "Stack",
          "stack_limit": 2,
          "stack_key": null
        }
      ]
    },
    {
      "chance": 1.0,
      "ppm": 0.0,
      "delay": 0.0,
      "radius_inner": -1.0,
      "radius_outer": -1.0,
      "requires_expression": "Power_DisallowSpeedBoost target.TokenOwned? !",
      "flags": [],
      "is_pvp": "EITHER",
      "eval_flags": 0,
      "templates": [
        {
          "attribs": [
            "JumpHeight"
          ],
          "type": "Magnitude",
          "application_type": "Immediate",
          "aspect": "Strength",
          "target": "AnyAffected",
          "table": "Ranged_Slow",
          "scale": 0.1,
          "duration": "60 seconds",
          "magnitude": 1.0,
          "delay": 0.0,
          "duration_expression": "",
          "magnitude_expression": "",
          "application_period": 0.0,
          "tick_chance": 1.0,
          "tick_mag_multiplier": 1.0,
          "tick_mag_additive": 0.0,
          "jit_requires": "",
          "caster_stack": "Individual",
          "stack": "Replace",
          "stack_limit": 2,
          "stack_key": null
        },
        {
          "attribs": [
            "RunningSpeed",
            "FlyingSpeed",
            "JumpingSpeed"
          ],
          "type": "Magnitude",
          "application_type": "Immediate",
          "aspect": "Current",
          "target": "AnyAffected",
          "table": "Ranged_Slow",
          "scale": 0.1,
          "duration": "60 seconds",
          "magnitude": 1.0,
          "delay": 0.0,
          "duration_expression": "",
          "magnitude_expression": "",
          "application_period": 0.0,
          "tick_chance": 1.0,
          "tick_mag_multiplier": 1.0,
          "tick_mag_additive": 0.0,
          "jit_requires": "",
          "caster_stack": "Individual",
          "stack": "Replace",
          "stack_limit": 2,
          "stack_key": null
        }
      ]
    }
  ],
  "available_level": 0,
  "powerset": "Controller_Buff.Kinetics"
}