{
  "key": "Blaster_Support.Tactical_Arrow",
  "display_name": "Tactical Arrow",
  "help": "Gain an advantage in combat with a combination of training techniques that boost your accuracy and movement skills in addition to Tactical Arrows tipped with a variety of payloads, which if used strategically, can dramatically alter a battle site.",
  "short_help": "Tactical Arrow",
  "icon": "tactical_arrow_set.ico",
  "powers": [
    "Blaster_Support.Tactical_Arrow.Eagle_Eye",
    "Blaster_Support.Tactical_Arrow.Electrified_Net_Arrow",
    "Blaster_Support.Tactical_Arrow.EMP_Arrow",
    "Blaster_Support.Tactical_Arrow.Flash_Arrow",
    "Blaster_Support.Tactical_Arrow.Glue_Arrow",
    "Blaster_Support.Tactical_Arrow.Gymnastics",
    "Blaster_Support.Tactical_Arrow.Ice_Arrow",
    "Blaster_Support.Tactical_Arrow.Quickness",
    "Blaster_Support.Tactical_Arrow.Upshot"
  ],
  "available_level": [
    19,
    0,
    27,
    15,
    0,
    29,
    3,
    23,
    9
  ],
  "power_display_names": [
    "Eagle Eye",
    "Electrified Net Arrow",
    "ESD Arrow",
    "Flash Arrow",
    "Glue Arrow",
    "Oil Slick Arrow",
    "Ice Arrow",
    "Gymnastics",
    "Upshot"
  ],
  "power_short_helps": [
    "Toggle: Self +ACC, +Perception, +Res(DeBuff ToHit), +Regeneration, +Recovery",
    "Ranged, DoT(Energy), Foe Immobilize, -Fly, -Recharge, -SPD, -Jump",
    "Ranged (Targeted AoE), Foe Disorient, -End, Special vs. Robots",
    "Ranged (Targeted AoE), Foe -Perception, -ToHit",
    "Ranged (Targeted AoE), DoT(Toxic), Foe -SPD, -Recharge, -Fly, -Jump",
    "Ranged (Location AoE), Foe Knockdown, -SPD, -Jump, +Special",
    "Ranged, DoT(Cold), Foe Hold, -SPD, -Recharge",
    "Toggle: Self +Recharge, +DEF(All), +SPD, +Res(Slow, Knockback)",
    "Self +DMG, +ToHit, +Recharge"
  ]
}