{
  "name": "Jaunt",
  "full_name": "Pool.Experimentation.Jaunt",
  "short_name": "Jaunt",
  "type": "Click",
  "display_name": "Jaunt",
  "display_fullname": "Pool Experimentation Jaunt",
  "display_help": "ZM2PYALD9Z9AYZMSCV8QSY7UAS",
  "display_short_help": "Click, Self Teleport",
  "icon": "experimentation_jaunt.png",
  "auto_issue": true,
  "auto_issue_keeps_level": false,
  "accuracy": 1.0,
  "effect_area": "Location",
  "max_targets_hit": 0,
  "radius": 0.0,
  "arc": 0.0,
  "range": 200.0,
  "range_secondary": 0.0,
  "activation_time": 1.0,
  "recharge_time": 10.0,
  "activate_period": 0.0,
  "endurance_cost": 13.0,
  "interrupt_time": 0.0,
  "target_type": "DeadMyPet",
  "target_type_secondary": "None",
  "targets_autohit": [
    "Self"
  ],
  "targets_affected": [
    "Self"
  ],
  "boosts_allowed": [],
  "allowed_boostset_cats": [],
  "cast_through": [],
  "num_allowed": 1,
  "requires": "Pool.Experimentation.Speed_of_Sound",
  "activate_requires": "",
  "target_requires": "",
  "attack_types": [],
  "effects": [
    {
      "chance": 1.0,
      "ppm": 0.0,
      "delay": 0.0,
      "radius_inner": -1.0,
      "radius_outer": -1.0,
      "requires_expression": "",
      "flags": [],
      "is_pvp": "EITHER",
      "eval_flags": 0,
      "templates": [
        {
          "attribs": [
            "Create_Entity"
          ],
          "type": "Magnitude",
          "application_type": "Immediate",
          "aspect": "Current",
          "target": "Self",
          "table": "Ranged_Ones",
          "scale": 0.0,
          "duration": "1 seconds",
          "magnitude": 1.0,
          "delay": 0.0,
          "duration_expression": "",
          "magnitude_expression": "",
          "application_period": 0.0,
          "tick_chance": 1.0,
          "tick_mag_multiplier": 1.0,
          "tick_mag_additive": 0.0,
          "jit_requires": "",
          "caster_stack": "Individual",
          "stack": "Stack",
          "stack_limit": 2,
          "stack_key": null
        },
        {
          "attribs": [
            "Teleport"
          ],
          "type": "Magnitude",
          "application_type": "Immediate",
          "aspect": "Current",
          "target": "Self",
          "table": "Ranged_Ones",
          "scale": 1.0,
          "duration": "0 seconds",
          "magnitude": 1.0,
          "delay": 0.0,
          "duration_expression": "",
          "magnitude_expression": "",
          "application_period": 0.0,
          "tick_chance": 1.0,
          "tick_mag_multiplier": 1.0,
          "tick_mag_additive": 0.0,
          "jit_requires": "",
          "caster_stack": "Individual",
          "stack": "Stack",
          "stack_limit": 2,
          "stack_key": null
        }
      ]
    },
    {
      "chance": 2.0,
      "ppm": 0.0,
      "delay": 0.0,
      "radius_inner": -1.0,
      "radius_outer": -1.0,
      "requires_expression": "",
      "flags": [
        "PVEOnly"
      ],
      "is_pvp": "PVE_ONLY",
      "eval_flags": 0,
      "templates": [
        {
          "attribs": [
            "Recharge_Power"
          ],
          "type": "Magnitude",
          "application_type": "Immediate",
          "aspect": "Current",
          "target": "Self",
          "table": "Ranged_Ones",
          "scale": 1.0,
          "duration": "0 seconds",
          "magnitude": 1.0,
          "delay": 0.0,
          "duration_expression": "",
          "magnitude_expression": "",
          "application_period": 0.0,
          "tick_chance": 1.0,
          "tick_mag_multiplier": 1.0,
          "tick_mag_additive": 0.0,
          "jit_requires": "",
          "caster_stack": "Individual",
          "stack": "Stack",
          "stack_limit": 2,
          "stack_key": null,
          "params": {
            "type": "Power",
            "power_names": [
              "Pool.Experimentation.Jaunt"
            ]
          }
        },
        {
          "attribs": [
            "Global_Chance_Mod"
          ],
          "type": "Magnitude",
          "application_type": "Immediate",
          "aspect": "Current",
          "target": "Self",
          "table": "Ranged_Ones",
          "scale": -1.0,
          "duration": "10 seconds",
          "magnitude": 1.0,
          "delay": 0.0,
          "duration_expression": "",
          "magnitude_expression": "",
          "application_period": 0.0,
          "tick_chance": 1.0,
          "tick_mag_multiplier": 1.0,
          "tick_mag_additive": 0.0,
          "jit_requires": "",
          "caster_stack": "Individual",
          "stack": "Stack",
          "stack_limit": 2,
          "stack_key": null
        }
      ]
    },
    {
      "chance": 1.0,
      "ppm": 0.0,
      "delay": 0.0,
      "radius_inner": -1.0,
      "radius_outer": -1.0,
      "requires_expression": "",
      "flags": [
        "PVPOnly"
      ],
      "is_pvp": "PVP_ONLY",
      "eval_flags": 0,
      "templates": [],
      "child_effects": [
        {
          "chance": 2.0,
          "ppm": 0.0,
          "delay": 0.0,
          "radius_inner": -1.0,
          "radius_outer": -1.0,
          "requires_expression": "",
          "flags": [],
          "is_pvp": "EITHER",
          "eval_flags": 0,
          "templates": [
            {
              "attribs": [
                "Recharge_Power"
              ],
              "type": "Magnitude",
              "application_type": "Immediate",
              "aspect": "Current",
              "target": "Self",
              "table": "Ranged_Ones",
              "scale": 1.0,
              "duration": "0 seconds",
              "magnitude": 1.0,
              "delay": 0.0,
              "duration_expression": "",
              "magnitude_expression": "",
              "application_period": 0.0,
              "tick_chance": 1.0,
              "tick_mag_multiplier": 1.0,
              "tick_mag_additive": 0.0,
              "jit_requires": "",
              "caster_stack": "Individual",
              "stack": "Stack",
              "stack_limit": 2,
              "stack_key": null,
              "params": {
                "type": "Power",
                "power_names": [
                  "Pool.Experimentation.Jaunt"
                ]
              }
            },
            {
              "attribs": [
                "Global_Chance_Mod"
              ],
              "type": "Magnitude",
              "application_type": "Immediate",
              "aspect": "Current",
              "target": "Self",
              "table": "Ranged_Ones",
              "scale": -1.0,
              "duration": "30 seconds",
              "magnitude": 1.0,
              "delay": 0.0,
              "duration_expression": "",
              "magnitude_expression": "",
              "application_period": 0.0,
              "tick_chance": 1.0,
              "tick_mag_multiplier": 1.0,
              "tick_mag_additive": 0.0,
              "jit_requires": "",
              "caster_stack": "Individual",
              "stack": "Stack",
              "stack_limit": 2,
              "stack_key": null
            }
          ]
        },
        {
          "chance": 1.0,
          "ppm": 0.0,
          "delay": 0.0,
          "radius_inner": -1.0,
          "radius_outer": -1.0,
          "requires_expression": "",
          "flags": [],
          "is_pvp": "EITHER",
          "eval_flags": 0,
          "templates": [
            {
              "attribs": [
                "Recharge_Power"
              ],
              "type": "Magnitude",
              "application_type": "Immediate",
              "aspect": "Current",
              "target": "Self",
              "table": "Ranged_Ones",
              "scale": 30.0,
              "duration": "0 seconds",
              "magnitude": 1.0,
              "delay": 0.0,
              "duration_expression": "",
              "magnitude_expression": "",
              "application_period": 0.0,
              "tick_chance": 1.0,
              "tick_mag_multiplier": 1.0,
              "tick_mag_additive": 0.0,
              "jit_requires": "",
              "caster_stack": "Individual",
              "stack": "Stack",
              "stack_limit": 2,
              "stack_key": null,
              "params": {
                "type": "Power",
                "power_names": [
                  "Pool.Experimentation.Jaunt"
                ]
              }
            }
          ]
        }
      ]
    }
  ],
  "available_level": 0,
  "powerset": "Pool.Experimentation"
}